[
  {
    "id": "mpxyuj6vr5xt",
    "title": "stash (@stash_pomichter) on X",
    "url": "https://x.com/stash_pomichter/status/2061811518824493075?s=20",
    "description": "An open source developer connecting all types of hardware using DimOS. \n\nSnapchat Spectacles + Robot dog vibe coded in &amp;lt;1 day.\n\nPlay with hardware and physical space like connecting lego bricks.",
    "thumbnail": "https://jf.x.com/images/media-preview/2061811518824493075",
    "tags": [],
    "platform": "x",
    "date": "2026-06-03"
  },
  {
    "id": "mpxyv794ud10",
    "title": "Gaku Shimizu / oji_chang (@oji_chang) on X",
    "url": "https://x.com/oji_chang/status/2061566137910100001?s=20",
    "description": "近所の散歩をエルデンリング化するアプリを試作。\n\nスマートグラスEven G2を着けて駅の近くに来ると、重厚なSEに合わせて眼の前に駅名がドンと表示。\n\nただの散歩なのに、新エリアを発見した感が生まれる。  \n\n（SEはスマホ側から再生）",
    "thumbnail": "https://jf.x.com/images/media-preview/2061566137910100001",
    "tags": [],
    "platform": "x",
    "date": "2026-06-03"
  }
]